TOPSIS_Calc_101866010/__init__.py
TOPSIS_Calc_101866010-0.0.1.dist-info/LICENSE.txt
TOPSIS_Calc_101866010-0.0.1.dist-info/METADATA
TOPSIS_Calc_101866010-0.0.1.dist-info/WHEEL
TOPSIS_Calc_101866010-0.0.1.dist-info/top_level.txt
TOPSIS_Calc_101866010-0.0.1.dist-info/RECORD
