Metadata-Version: 2.1
Name: TOPSIS-Calc-101866010
Version: 0.0.1
Summary: TOPSIS score calculation
Home-page: https://github.com/pranavanand24/
Author: Pranav Anand
Author-email: pranavanand2410@gmail.com
License: UNKNOWN
Platform: UNKNOWN
Classifier: Programming Language :: Python :: 3
Classifier: License :: OSI Approved :: MIT License
Classifier: Operating System :: OS Independent
